{"id": 13728571, "resource_state": 3, "name": "Lepence - Pilisszentl\u00e1szl\u00f3 emelked\u0151", "activity_type": "Ride", "distance": 7718.2, "average_grade": 3.9, "maximum_grade": 19.8, "elevation_high": 424.6, "elevation_low": 124.5, "start_latlng": [47.764313, 18.954023], "end_latlng": [47.724162, 18.978635], "elevation_profile": "https://d3o5xota0a1fcr.cloudfront.net/v6/charts/GGQH3ZLQHX3LNS75YXTS4E5K7MKDGJY6SROTYMXVD3SPJ4XIIHUZ2ZNLK45OF5FLRF5YJ4LJ3IVDTSKW4BEP6===", "climb_category": 2, "city": "Visegr\u00e1d", "state": null, "country": "Hungary", "private": false, "hazardous": false, "starred": false, "created_at": "2016-11-29T09:55:36Z", "updated_at": "2021-05-20T08:04:03Z", "total_elevation_gain": 315.2, "map": {"id": "s13728571", "polyline": "}}obHs}trBd@KVK~@u@~@aA`A{AnAiA|@g@VIf@GX?f@DhAZb@TxBzAvChA^V\\Z^b@`@j@~ApCn@~@z@nBn@pBb@dC@l@C`AGnA[dCBlAPhA\\nAbBfErA|DzA~C`@dA~@jBv@dAnAvAZTh@ZbAb@tA\\z@N^BxAV~@FdA@b@DxFz@v@NdCZpB^jABl@ClAObAQn@Ur@[r@a@pA_ArAu@b@]RInA]TEjAKj@@t@HTFj@Pj@XbFvDn@\\r@ZbAVr@F|@EfA[v@e@t@s@n@_AXg@`AoAfA{BTo@P]h@q@|A}Bz@sCJWV]t@k@h@[XWp@w@h@}@`@YZGZ?p@H\\J`@B`@IFGNUF[?_@EYKSGCSAUD]L_@@UOOYOq@Gs@CeADw@PmAtB}HvBkG~@cCbAuDHQV]XSf@OfFw@v@Q^M`BeA^I`@BTHRNpA`B`@Zd@RdB^XLTVNXPn@JvAJv@~@lBNPH@FAXSR]FQf@yBj@kDJ]d@cAb@e@ZQ|Bo@RI\\_@Xi@BO?c@Mq@IQWO]Gc@QUSU[S_@oAoDKe@Eg@By@Nu@r@iCVo@x@iCVq@Jc@De@Ae@Oa@_@c@{@{@U_@Qa@Kg@Ci@DsADQLa@f@s@Ti@^g@P_@BO@a@YcBEa@?w@Ju@Tm@LYFIZOVST]HOBQAQMc@S[w@_AS_@Mc@Kg@G_A?k@BaAJaAXiB^cB`@aBbAkE`@kAj@sBrAoF\\cA`@mBh@iBj@cBP_@bCwD\\q@`@iAr@oC", "resource_state": 3}, "effort_count": 7713, "athlete_count": 1935, "star_count": 4, "athlete_segment_stats": {"pr_elapsed_time": null, "pr_date": null, "pr_activity_id": null, "effort_count": 0}, "xoms": {"kom": "16:37", "qom": "19:58", "destination": {"href": "strava://segments/13728571/leaderboard", "type": "overall", "name": "All-Time"}, "overall": "16:37"}, "local_legend": {"athlete_id": 5908833, "title": "Tibor _gauntlet_ M\u00e9hes", "profile": "https://dgalywyr863hv.cloudfront.net/pictures/athletes/5908833/3392853/1/large.jpg", "effort_description": "9 efforts in the last 90 days", "effort_count": "9", "effort_counts": {"overall": "9 efforts", "female": "2 efforts"}, "destination": "strava://segments/13728571/local_legend?categories%5B%5D=overall"}}